rtl/UARTRX.vhdl
--
-- simple UART receiver, bit clock is the clk_in divided by 50
--
--
library IEEE;
use IEEE.std_logic_1164.all;
use IEEE.numeric_std.all;

entity UARTRX is
	port (
		clk_in      : in  std_logic                     := '0'; -- 50 MHz clock
		data_o      : out  std_logic_vector(7 downto 0);
		data_rdy_o  : out  std_logic;
		data_ovr_o  : out  std_logic;
        data_ack_in : in std_logic;
        
        bits_o      : out  std_logic_vector(7 downto 0);
		bit_cnt_o   : out  std_logic_vector(7 downto 0);
        
		rx_in       : in std_logic                           
	);
end entity UARTRX;

architecture logic of UARTRX is

    signal state  : integer range 0 to 15 := 0;
    signal rxbuff : std_logic_vector(7 downto 0) := "00000000";
    signal bit_cnt : integer range 0 to 63 := 0;
    signal old_rx : std_logic := '0';
    signal samples : std_logic_vector(2 downto 0) := "000";
    signal majority : std_logic;
    signal data_rdy : std_logic := '0';
    signal data_ovr : std_logic := '0';

    signal bits     : integer range 0 to 255 := 0;
    
    
begin

    majority <= (samples(0) and samples(1)) or (samples(1) and samples(2)) or (samples(0) and samples(2));
    data_rdy_o <= data_rdy;
    data_ovr_o <= data_ovr;
    data_o <= rxbuff(7 downto 0);
    
    bits_o <= std_logic_vector(to_unsigned(bits, 8));
    bit_cnt_o <= std_logic_vector(to_unsigned(bit_cnt, 8));
     
    process(clk_in) 
    begin
        if (rising_edge(clk_in)) then
            -- sampling
            old_rx <= rx_in;
                       
            if state = 0 then -- wait for start condition
                bit_cnt <= 0;
                if old_rx = '1' and rx_in = '0' then 
                    state <= 1;
                    bits <= (bits + 1) mod 256;
                end if;
            else
                if bit_cnt = 49 then
                    bit_cnt <= 0;
                else
                    bit_cnt <= bit_cnt + 1;
                end if;
            end if;            
            
            if bit_cnt = 49 then
                case state is
                    when 0 => null; -- wait for start condition

                    when 1 => -- start bit
                            state <= state + 1;
                    when 2 | 3 | 4 | 5 | 6 | 7 | 8 =>                   
                        rxbuff <= majority & rxbuff(7 downto 1); -- shift
                        state <= state + 1;
                        bits <= (bits + 1) mod 256;
                    when others => -- last bit
                        rxbuff <= majority & rxbuff(7 downto 1); -- shift
                        state <= 0;
                        if data_rdy = '1' then
                            data_ovr <= '1';
                        end if;
                        data_rdy <= '1';
                end case;
            end if;
            if bit_cnt = 15 then
                samples(0) <= old_rx;
            end if;
            if bit_cnt = 25 then
                samples(1) <= old_rx;
            end if;
            if bit_cnt = 35 then
                samples(2) <= old_rx;
            end if;
            -- data_rdy
            if data_ack_in = '1' then 
                data_rdy <= '0';
            end if;
        end if;
    end process;
    
    
end architecture;

testbenches/UARTRX_tb.vhdl

library ieee;
use ieee.std_logic_1164.all;
use ieee.numeric_std.all;

entity UARTRX_tb is

end UARTRX_tb;

architecture logic of UARTRX_tb is
    component UARTRX is
        port (
            clk_in      : in  std_logic; -- 50 MHz clock
            data_o      : out  std_logic_vector(7 downto 0);
            data_rdy_o  : out  std_logic;
            data_ovr_o  : out  std_logic;
            data_ack_in : in std_logic;
            bits_o      : out  std_logic_vector(7 downto 0);
            bit_cnt_o   : out  std_logic_vector(7 downto 0);
            rx_in       : in std_logic
        );
        end component UARTRX;
         
        signal clk_10MHz    : std_logic;
        signal clk_12MHz    : std_logic;
        signal clk_50MHz    : std_logic;
        signal clk_1MHz     : std_logic;
        signal resetn       : std_logic; -- pll locked used as reset signal, reset active low
        signal tx_data      : std_logic_vector(7 downto 0);
        signal rx_data      : std_logic_vector(7 downto 0);

        signal rx_in        : std_logic := '1';
        signal tx_start     : std_logic;
        signal tx_busy      : std_logic;
        signal rx_ready     : std_logic;
        signal rx_overrun   : std_logic;
        signal rx_ack       : std_logic;
        signal bits         : std_logic_vector(7 downto 0);
        signal bit_cnt      : std_logic_vector(7 downto 0);
        signal d5           : std_logic_vector(3 downto 0);
     
begin

    
    irx : UARTRX port map(
        clk_in      => clk_50MHz,
        data_o      => rx_data,
        data_rdy_o  => rx_ready,
        data_ovr_o  => rx_overrun,
        data_ack_in => rx_ack,
        bits_o      => bits,
		bit_cnt_o   => bit_cnt,
		
        rx_in       => rx_in
    );
    
    process -- clk 50 MHz
        begin
            clk_50MHz        <= '0';
            wait for 10 ns;
            clk_50MHz        <= '1';
            wait for 10 ns;
        end process;
    -- RX
    process 
        begin
            rx_in  <= '1';
            wait for 777 ns;
            rx_in <= '0';
            wait for 1 us;
            rx_in <= '1';
            wait for 1 us;
            rx_in <= '0';
            wait for 1 us;
            rx_in <= '0';
            wait for 1 us;
            rx_in <= '0';
            wait for 1 us;
            rx_in <= '0';
            wait for 1 us;
            rx_in <= '0';
            wait for 1 us;
            rx_in <= '0';
            wait for 1 us;
            rx_in <= '0';
            wait for 1 us;
            rx_in <= '1';
            wait for 1 us;
            rx_in <= '1';
            wait;
        end process;

        
end architecture logic;

testbenches/UARTRX_tb.vcd
$date
  Thu Dec 31 10:12:15 2020
$end
$version
  GHDL v0
$end
$timescale
  1 fs
$end
$scope module standard $end
$upscope $end
$scope module textio $end
$upscope $end
$scope module std_logic_1164 $end
$upscope $end
$scope module numeric_std $end
$upscope $end
$scope module uartrx_tb $end
$var reg 1 ! clk_10mhz $end
$var reg 1 " clk_12mhz $end
$var reg 1 # clk_50mhz $end
$var reg 1 $ clk_1mhz $end
$var reg 1 % resetn $end
$var reg 8 & tx_data[7:0] $end
$var reg 8 ' rx_data[7:0] $end
$var reg 1 ( rx_in $end
$var reg 1 ) tx_start $end
$var reg 1 * tx_busy $end
$var reg 1 + rx_ready $end
$var reg 1 , rx_overrun $end
$var reg 1 - rx_ack $end
$var reg 8 . bits[7:0] $end
$var reg 8 / bit_cnt[7:0] $end
$var reg 4 0 d5[3:0] $end
$scope module irx $end
$var reg 1 1 clk_in $end
$var reg 8 2 data_o[7:0] $end
$var reg 1 3 data_rdy_o $end
$var reg 1 4 data_ovr_o $end
$var reg 1 5 data_ack_in $end
$var reg 8 6 bits_o[7:0] $end
$var reg 8 7 bit_cnt_o[7:0] $end
$var reg 1 8 rx_in $end
$var integer 32 9 state $end
$var reg 8 : rxbuff[7:0] $end
$var integer 32 ; bit_cnt $end
$var reg 1 < old_rx $end
$var reg 3 = samples[2:0] $end
$var reg 1 > majority $end
$var reg 1 ? data_rdy $end
$var reg 1 @ data_ovr $end
$var integer 32 A bits $end
$upscope $end
$upscope $end
$enddefinitions $end
#0
U!
U"
0#
U$
U%
bUUUUUUUU &
b00000000 '
1(
U)
U*
0+
0,
U-
b00000000 .
b00000000 /
bUUUU 0
01
b00000000 2
03
04
U5
b00000000 6
b00000000 7
18
b0 9
b00000000 :
b0 ;
0<
b000 =
0>
0?
0@
b0 A
#10000000
1#
11
1<
#20000000
0#
01
#30000000
1#
11
#40000000
0#
01
#50000000
1#
11
#60000000
0#
01
#70000000
1#
11
#80000000
0#
01
#90000000
1#
11
#100000000
0#
01
#110000000
1#
11
#120000000
0#
01
#130000000
1#
11
#140000000
0#
01
#150000000
1#
11
#160000000
0#
01
#170000000
1#
11
#180000000
0#
01
#190000000
1#
11
#200000000
0#
01
#210000000
1#
11
#220000000
0#
01
#230000000
1#
11
#240000000
0#
01
#250000000
1#
11
#260000000
0#
01
#270000000
1#
11
#280000000
0#
01
#290000000
1#
11
#300000000
0#
01
#310000000
1#
11
#320000000
0#
01
#330000000
1#
11
#340000000
0#
01
#350000000
1#
11
#360000000
0#
01
#370000000
1#
11
#380000000
0#
01
#390000000
1#
11
#400000000
0#
01
#410000000
1#
11
#420000000
0#
01
#430000000
1#
11
#440000000
0#
01
#450000000
1#
11
#460000000
0#
01
#470000000
1#
11
#480000000
0#
01
#490000000
1#
11
#500000000
0#
01
#510000000
1#
11
#520000000
0#
01
#530000000
1#
11
#540000000
0#
01
#550000000
1#
11
#560000000
0#
01
#570000000
1#
11
#580000000
0#
01
#590000000
1#
11
#600000000
0#
01
#610000000
1#
11
#620000000
0#
01
#630000000
1#
11
#640000000
0#
01
#650000000
1#
11
#660000000
0#
01
#670000000
1#
11
#680000000
0#
01
#690000000
1#
11
#700000000
0#
01
#710000000
1#
11
#720000000
0#
01
#730000000
1#
11
#740000000
0#
01
#750000000
1#
11
#760000000
0#
01
#770000000
1#
11
#777000000
0(
08
#780000000
0#
01
#790000000
1#
b00000001 .
11
b00000001 6
b1 9
0<
b1 A
#800000000
0#
01
#810000000
1#
b00000001 /
11
b00000001 7
b1 ;
#820000000
0#
01
#830000000
1#
b00000010 /
11
b00000010 7
b10 ;
#840000000
0#
01
#850000000
1#
b00000011 /
11
b00000011 7
b11 ;
#860000000
0#
01
#870000000
1#
b00000100 /
11
b00000100 7
b100 ;
#880000000
0#
01
#890000000
1#
b00000101 /
11
b00000101 7
b101 ;
#900000000
0#
01
#910000000
1#
b00000110 /
11
b00000110 7
b110 ;
#920000000
0#
01
#930000000
1#
b00000111 /
11
b00000111 7
b111 ;
#940000000
0#
01
#950000000
1#
b00001000 /
11
b00001000 7
b1000 ;
#960000000
0#
01
#970000000
1#
b00001001 /
11
b00001001 7
b1001 ;
#980000000
0#
01
#990000000
1#
b00001010 /
11
b00001010 7
b1010 ;
#1000000000
0#
01
#1010000000
1#
b00001011 /
11
b00001011 7
b1011 ;
#1020000000
0#
01
#1030000000
1#
b00001100 /
11
b00001100 7
b1100 ;
#1040000000
0#
01
#1050000000
1#
b00001101 /
11
b00001101 7
b1101 ;
#1060000000
0#
01
#1070000000
1#
b00001110 /
11
b00001110 7
b1110 ;
#1080000000
0#
01
#1090000000
1#
b00001111 /
11
b00001111 7
b1111 ;
#1100000000
0#
01
#1110000000
1#
b00010000 /
11
b00010000 7
b10000 ;
#1120000000
0#
01
#1130000000
1#
b00010001 /
11
b00010001 7
b10001 ;
#1140000000
0#
01
#1150000000
1#
b00010010 /
11
b00010010 7
b10010 ;
#1160000000
0#
01
#1170000000
1#
b00010011 /
11
b00010011 7
b10011 ;
#1180000000
0#
01
#1190000000
1#
b00010100 /
11
b00010100 7
b10100 ;
#1200000000
0#
01
#1210000000
1#
b00010101 /
11
b00010101 7
b10101 ;
#1220000000
0#
01
#1230000000
1#
b00010110 /
11
b00010110 7
b10110 ;
#1240000000
0#
01
#1250000000
1#
b00010111 /
11
b00010111 7
b10111 ;
#1260000000
0#
01
#1270000000
1#
b00011000 /
11
b00011000 7
b11000 ;
#1280000000
0#
01
#1290000000
1#
b00011001 /
11
b00011001 7
b11001 ;
#1300000000
0#
01
#1310000000
1#
b00011010 /
11
b00011010 7
b11010 ;
#1320000000
0#
01
#1330000000
1#
b00011011 /
11
b00011011 7
b11011 ;
#1340000000
0#
01
#1350000000
1#
b00011100 /
11
b00011100 7
b11100 ;
#1360000000
0#
01
#1370000000
1#
b00011101 /
11
b00011101 7
b11101 ;
#1380000000
0#
01
#1390000000
1#
b00011110 /
11
b00011110 7
b11110 ;
#1400000000
0#
01
#1410000000
1#
b00011111 /
11
b00011111 7
b11111 ;
#1420000000
0#
01
#1430000000
1#
b00100000 /
11
b00100000 7
b100000 ;
#1440000000
0#
01
#1450000000
1#
b00100001 /
11
b00100001 7
b100001 ;
#1460000000
0#
01
#1470000000
1#
b00100010 /
11
b00100010 7
b100010 ;
#1480000000
0#
01
#1490000000
1#
b00100011 /
11
b00100011 7
b100011 ;
#1500000000
0#
01
#1510000000
1#
b00100100 /
11
b00100100 7
b100100 ;
#1520000000
0#
01
#1530000000
1#
b00100101 /
11
b00100101 7
b100101 ;
#1540000000
0#
01
#1550000000
1#
b00100110 /
11
b00100110 7
b100110 ;
#1560000000
0#
01
#1570000000
1#
b00100111 /
11
b00100111 7
b100111 ;
#1580000000
0#
01
#1590000000
1#
b00101000 /
11
b00101000 7
b101000 ;
#1600000000
0#
01
#1610000000
1#
b00101001 /
11
b00101001 7
b101001 ;
#1620000000
0#
01
#1630000000
1#
b00101010 /
11
b00101010 7
b101010 ;
#1640000000
0#
01
#1650000000
1#
b00101011 /
11
b00101011 7
b101011 ;
#1660000000
0#
01
#1670000000
1#
b00101100 /
11
b00101100 7
b101100 ;
#1680000000
0#
01
#1690000000
1#
b00101101 /
11
b00101101 7
b101101 ;
#1700000000
0#
01
#1710000000
1#
b00101110 /
11
b00101110 7
b101110 ;
#1720000000
0#
01
#1730000000
1#
b00101111 /
11
b00101111 7
b101111 ;
#1740000000
0#
01
#1750000000
1#
b00110000 /
11
b00110000 7
b110000 ;
#1760000000
0#
01
#1770000000
1#
b00110001 /
11
b00110001 7
b110001 ;
#1777000000
1(
18
#1780000000
0#
01
#1790000000
1#
b00000000 /
11
b00000000 7
b10 9
b0 ;
1<
#1800000000
0#
01
#1810000000
1#
b00000001 /
11
b00000001 7
b1 ;
#1820000000
0#
01
#1830000000
1#
b00000010 /
11
b00000010 7
b10 ;
#1840000000
0#
01
#1850000000
1#
b00000011 /
11
b00000011 7
b11 ;
#1860000000
0#
01
#1870000000
1#
b00000100 /
11
b00000100 7
b100 ;
#1880000000
0#
01
#1890000000
1#
b00000101 /
11
b00000101 7
b101 ;
#1900000000
0#
01
#1910000000
1#
b00000110 /
11
b00000110 7
b110 ;
#1920000000
0#
01
#1930000000
1#
b00000111 /
11
b00000111 7
b111 ;
#1940000000
0#
01
#1950000000
1#
b00001000 /
11
b00001000 7
b1000 ;
#1960000000
0#
01
#1970000000
1#
b00001001 /
11
b00001001 7
b1001 ;
#1980000000
0#
01
#1990000000
1#
b00001010 /
11
b00001010 7
b1010 ;
#2000000000
0#
01
#2010000000
1#
b00001011 /
11
b00001011 7
b1011 ;
#2020000000
0#
01
#2030000000
1#
b00001100 /
11
b00001100 7
b1100 ;
#2040000000
0#
01
#2050000000
1#
b00001101 /
11
b00001101 7
b1101 ;
#2060000000
0#
01
#2070000000
1#
b00001110 /
11
b00001110 7
b1110 ;
#2080000000
0#
01
#2090000000
1#
b00001111 /
11
b00001111 7
b1111 ;
#2100000000
0#
01
#2110000000
1#
b00010000 /
11
b00010000 7
b10000 ;
b001 =
#2120000000
0#
01
#2130000000
1#
b00010001 /
11
b00010001 7
b10001 ;
#2140000000
0#
01
#2150000000
1#
b00010010 /
11
b00010010 7
b10010 ;
#2160000000
0#
01
#2170000000
1#
b00010011 /
11
b00010011 7
b10011 ;
#2180000000
0#
01
#2190000000
1#
b00010100 /
11
b00010100 7
b10100 ;
#2200000000
0#
01
#2210000000
1#
b00010101 /
11
b00010101 7
b10101 ;
#2220000000
0#
01
#2230000000
1#
b00010110 /
11
b00010110 7
b10110 ;
#2240000000
0#
01
#2250000000
1#
b00010111 /
11
b00010111 7
b10111 ;
#2260000000
0#
01
#2270000000
1#
b00011000 /
11
b00011000 7
b11000 ;
#2280000000
0#
01
#2290000000
1#
b00011001 /
11
b00011001 7
b11001 ;
#2300000000
0#
01
#2310000000
1#
b00011010 /
11
b00011010 7
b11010 ;
b011 =
1>
#2320000000
0#
01
#2330000000
1#
b00011011 /
11
b00011011 7
b11011 ;
#2340000000
0#
01
#2350000000
1#
b00011100 /
11
b00011100 7
b11100 ;
#2360000000
0#
01
#2370000000
1#
b00011101 /
11
b00011101 7
b11101 ;
#2380000000
0#
01
#2390000000
1#
b00011110 /
11
b00011110 7
b11110 ;
#2400000000
0#
01
#2410000000
1#
b00011111 /
11
b00011111 7
b11111 ;
#2420000000
0#
01
#2430000000
1#
b00100000 /
11
b00100000 7
b100000 ;
#2440000000
0#
01
#2450000000
1#
b00100001 /
11
b00100001 7
b100001 ;
#2460000000
0#
01
#2470000000
1#
b00100010 /
11
b00100010 7
b100010 ;
#2480000000
0#
01
#2490000000
1#
b00100011 /
11
b00100011 7
b100011 ;
#2500000000
0#
01
#2510000000
1#
b00100100 /
11
b00100100 7
b100100 ;
b111 =
#2520000000
0#
01
#2530000000
1#
b00100101 /
11
b00100101 7
b100101 ;
#2540000000
0#
01
#2550000000
1#
b00100110 /
11
b00100110 7
b100110 ;
#2560000000
0#
01
#2570000000
1#
b00100111 /
11
b00100111 7
b100111 ;
#2580000000
0#
01
#2590000000
1#
b00101000 /
11
b00101000 7
b101000 ;
#2600000000
0#
01
#2610000000
1#
b00101001 /
11
b00101001 7
b101001 ;
#2620000000
0#
01
#2630000000
1#
b00101010 /
11
b00101010 7
b101010 ;
#2640000000
0#
01
#2650000000
1#
b00101011 /
11
b00101011 7
b101011 ;
#2660000000
0#
01
#2670000000
1#
b00101100 /
11
b00101100 7
b101100 ;
#2680000000
0#
01
#2690000000
1#
b00101101 /
11
b00101101 7
b101101 ;
#2700000000
0#
01
#2710000000
1#
b00101110 /
11
b00101110 7
b101110 ;
#2720000000
0#
01
#2730000000
1#
b00101111 /
11
b00101111 7
b101111 ;
#2740000000
0#
01
#2750000000
1#
b00110000 /
11
b00110000 7
b110000 ;
#2760000000
0#
01
#2770000000
1#
b00110001 /
11
b00110001 7
b110001 ;
#2777000000
0(
08
#2780000000
0#
01
#2790000000
1#
b10000000 '
b00000010 .
b00000000 /
11
b10000000 2
b00000010 6
b00000000 7
b11 9
b10000000 :
b0 ;
0<
b10 A
#2800000000
0#
01
#2810000000
1#
b00000001 /
11
b00000001 7
b1 ;
#2820000000
0#
01
#2830000000
1#
b00000010 /
11
b00000010 7
b10 ;
#2840000000
0#
01
#2850000000
1#
b00000011 /
11
b00000011 7
b11 ;
#2860000000
0#
01
#2870000000
1#
b00000100 /
11
b00000100 7
b100 ;
#2880000000
0#
01
#2890000000
1#
b00000101 /
11
b00000101 7
b101 ;
#2900000000
0#
01
#2910000000
1#
b00000110 /
11
b00000110 7
b110 ;
#2920000000
0#
01
#2930000000
1#
b00000111 /
11
b00000111 7
b111 ;
#2940000000
0#
01
#2950000000
1#
b00001000 /
11
b00001000 7
b1000 ;
#2960000000
0#
01
#2970000000
1#
b00001001 /
11
b00001001 7
b1001 ;
#2980000000
0#
01
#2990000000
1#
b00001010 /
11
b00001010 7
b1010 ;
#3000000000
0#
01
#3010000000
1#
b00001011 /
11
b00001011 7
b1011 ;
#3020000000
0#
01
#3030000000
1#
b00001100 /
11
b00001100 7
b1100 ;
#3040000000
0#
01
#3050000000
1#
b00001101 /
11
b00001101 7
b1101 ;
#3060000000
0#
01
#3070000000
1#
b00001110 /
11
b00001110 7
b1110 ;
#3080000000
0#
01
#3090000000
1#
b00001111 /
11
b00001111 7
b1111 ;
#3100000000
0#
01
#3110000000
1#
b00010000 /
11
b00010000 7
b10000 ;
b110 =
#3120000000
0#
01
#3130000000
1#
b00010001 /
11
b00010001 7
b10001 ;
#3140000000
0#
01
#3150000000
1#
b00010010 /
11
b00010010 7
b10010 ;
#3160000000
0#
01
#3170000000
1#
b00010011 /
11
b00010011 7
b10011 ;
#3180000000
0#
01
#3190000000
1#
b00010100 /
11
b00010100 7
b10100 ;
#3200000000
0#
01
#3210000000
1#
b00010101 /
11
b00010101 7
b10101 ;
#3220000000
0#
01
#3230000000
1#
b00010110 /
11
b00010110 7
b10110 ;
#3240000000
0#
01
#3250000000
1#
b00010111 /
11
b00010111 7
b10111 ;
#3260000000
0#
01
#3270000000
1#
b00011000 /
11
b00011000 7
b11000 ;
#3280000000
0#
01
#3290000000
1#
b00011001 /
11
b00011001 7
b11001 ;
#3300000000
0#
01
#3310000000
1#
b00011010 /
11
b00011010 7
b11010 ;
b100 =
0>
#3320000000
0#
01
#3330000000
1#
b00011011 /
11
b00011011 7
b11011 ;
#3340000000
0#
01
#3350000000
1#
b00011100 /
11
b00011100 7
b11100 ;
#3360000000
0#
01
#3370000000
1#
b00011101 /
11
b00011101 7
b11101 ;
#3380000000
0#
01
#3390000000
1#
b00011110 /
11
b00011110 7
b11110 ;
#3400000000
0#
01
#3410000000
1#
b00011111 /
11
b00011111 7
b11111 ;
#3420000000
0#
01
#3430000000
1#
b00100000 /
11
b00100000 7
b100000 ;
#3440000000
0#
01
#3450000000
1#
b00100001 /
11
b00100001 7
b100001 ;
#3460000000
0#
01
#3470000000
1#
b00100010 /
11
b00100010 7
b100010 ;
#3480000000
0#
01
#3490000000
1#
b00100011 /
11
b00100011 7
b100011 ;
#3500000000
0#
01
#3510000000
1#
b00100100 /
11
b00100100 7
b100100 ;
b000 =
#3520000000
0#
01
#3530000000
1#
b00100101 /
11
b00100101 7
b100101 ;
#3540000000
0#
01
#3550000000
1#
b00100110 /
11
b00100110 7
b100110 ;
#3560000000
0#
01
#3570000000
1#
b00100111 /
11
b00100111 7
b100111 ;
#3580000000
0#
01
#3590000000
1#
b00101000 /
11
b00101000 7
b101000 ;
#3600000000
0#
01
#3610000000
1#
b00101001 /
11
b00101001 7
b101001 ;
#3620000000
0#
01
#3630000000
1#
b00101010 /
11
b00101010 7
b101010 ;
#3640000000
0#
01
#3650000000
1#
b00101011 /
11
b00101011 7
b101011 ;
#3660000000
0#
01
#3670000000
1#
b00101100 /
11
b00101100 7
b101100 ;
#3680000000
0#
01
#3690000000
1#
b00101101 /
11
b00101101 7
b101101 ;
#3700000000
0#
01
#3710000000
1#
b00101110 /
11
b00101110 7
b101110 ;
#3720000000
0#
01
#3730000000
1#
b00101111 /
11
b00101111 7
b101111 ;
#3740000000
0#
01
#3750000000
1#
b00110000 /
11
b00110000 7
b110000 ;
#3760000000
0#
01
#3770000000
1#
b00110001 /
11
b00110001 7
b110001 ;
#3777000000
#3780000000
0#
01
#3790000000
1#
b01000000 '
b00000011 .
b00000000 /
11
b01000000 2
b00000011 6
b00000000 7
b100 9
b01000000 :
b0 ;
b11 A
#3800000000
0#
01
#3810000000
1#
b00000001 /
11
b00000001 7
b1 ;
#3820000000
0#
01
#3830000000
1#
b00000010 /
11
b00000010 7
b10 ;
#3840000000
0#
01
#3850000000
1#
b00000011 /
11
b00000011 7
b11 ;
#3860000000
0#
01
#3870000000
1#
b00000100 /
11
b00000100 7
b100 ;
#3880000000
0#
01
#3890000000
1#
b00000101 /
11
b00000101 7
b101 ;
#3900000000
0#
01
#3910000000
1#
b00000110 /
11
b00000110 7
b110 ;
#3920000000
0#
01
#3930000000
1#
b00000111 /
11
b00000111 7
b111 ;
#3940000000
0#
01
#3950000000
1#
b00001000 /
11
b00001000 7
b1000 ;
#3960000000
0#
01
#3970000000
1#
b00001001 /
11
b00001001 7
b1001 ;
#3980000000
0#
01
#3990000000
1#
b00001010 /
11
b00001010 7
b1010 ;
#4000000000
0#
01
#4010000000
1#
b00001011 /
11
b00001011 7
b1011 ;
#4020000000
0#
01
#4030000000
1#
b00001100 /
11
b00001100 7
b1100 ;
#4040000000
0#
01
#4050000000
1#
b00001101 /
11
b00001101 7
b1101 ;
#4060000000
0#
01
#4070000000
1#
b00001110 /
11
b00001110 7
b1110 ;
#4080000000
0#
01
#4090000000
1#
b00001111 /
11
b00001111 7
b1111 ;
#4100000000
0#
01
#4110000000
1#
b00010000 /
11
b00010000 7
b10000 ;
#4120000000
0#
01
#4130000000
1#
b00010001 /
11
b00010001 7
b10001 ;
#4140000000
0#
01
#4150000000
1#
b00010010 /
11
b00010010 7
b10010 ;
#4160000000
0#
01
#4170000000
1#
b00010011 /
11
b00010011 7
b10011 ;
#4180000000
0#
01
#4190000000
1#
b00010100 /
11
b00010100 7
b10100 ;
#4200000000
0#
01
#4210000000
1#
b00010101 /
11
b00010101 7
b10101 ;
#4220000000
0#
01
#4230000000
1#
b00010110 /
11
b00010110 7
b10110 ;
#4240000000
0#
01
#4250000000
1#
b00010111 /
11
b00010111 7
b10111 ;
#4260000000
0#
01
#4270000000
1#
b00011000 /
11
b00011000 7
b11000 ;
#4280000000
0#
01
#4290000000
1#
b00011001 /
11
b00011001 7
b11001 ;
#4300000000
0#
01
#4310000000
1#
b00011010 /
11
b00011010 7
b11010 ;
#4320000000
0#
01
#4330000000
1#
b00011011 /
11
b00011011 7
b11011 ;
#4340000000
0#
01
#4350000000
1#
b00011100 /
11
b00011100 7
b11100 ;
#4360000000
0#
01
#4370000000
1#
b00011101 /
11
b00011101 7
b11101 ;
#4380000000
0#
01
#4390000000
1#
b00011110 /
11
b00011110 7
b11110 ;
#4400000000
0#
01
#4410000000
1#
b00011111 /
11
b00011111 7
b11111 ;
#4420000000
0#
01
#4430000000
1#
b00100000 /
11
b00100000 7
b100000 ;
#4440000000
0#
01
#4450000000
1#
b00100001 /
11
b00100001 7
b100001 ;
#4460000000
0#
01
#4470000000
1#
b00100010 /
11
b00100010 7
b100010 ;
#4480000000
0#
01
#4490000000
1#
b00100011 /
11
b00100011 7
b100011 ;
#4500000000
0#
01
#4510000000
1#
b00100100 /
11
b00100100 7
b100100 ;
#4520000000
0#
01
#4530000000
1#
b00100101 /
11
b00100101 7
b100101 ;
#4540000000
0#
01
#4550000000
1#
b00100110 /
11
b00100110 7
b100110 ;
#4560000000
0#
01
#4570000000
1#
b00100111 /
11
b00100111 7
b100111 ;
#4580000000
0#
01
#4590000000
1#
b00101000 /
11
b00101000 7
b101000 ;
#4600000000
0#
01
#4610000000
1#
b00101001 /
11
b00101001 7
b101001 ;
#4620000000
0#
01
#4630000000
1#
b00101010 /
11
b00101010 7
b101010 ;
#4640000000
0#
01
#4650000000
1#
b00101011 /
11
b00101011 7
b101011 ;
#4660000000
0#
01
#4670000000
1#
b00101100 /
11
b00101100 7
b101100 ;
#4680000000
0#
01
#4690000000
1#
b00101101 /
11
b00101101 7
b101101 ;
#4700000000
0#
01
#4710000000
1#
b00101110 /
11
b00101110 7
b101110 ;
#4720000000
0#
01
#4730000000
1#
b00101111 /
11
b00101111 7
b101111 ;
#4740000000
0#
01
#4750000000
1#
b00110000 /
11
b00110000 7
b110000 ;
#4760000000
0#
01
#4770000000
1#
b00110001 /
11
b00110001 7
b110001 ;
#4777000000
#4780000000
0#
01
#4790000000
1#
b00100000 '
b00000100 .
b00000000 /
11
b00100000 2
b00000100 6
b00000000 7
b101 9
b00100000 :
b0 ;
b100 A
#4800000000
0#
01
#4810000000
1#
b00000001 /
11
b00000001 7
b1 ;
#4820000000
0#
01
#4830000000
1#
b00000010 /
11
b00000010 7
b10 ;
#4840000000
0#
01
#4850000000
1#
b00000011 /
11
b00000011 7
b11 ;
#4860000000
0#
01
#4870000000
1#
b00000100 /
11
b00000100 7
b100 ;
#4880000000
0#
01
#4890000000
1#
b00000101 /
11
b00000101 7
b101 ;
#4900000000
0#
01
#4910000000
1#
b00000110 /
11
b00000110 7
b110 ;
#4920000000
0#
01
#4930000000
1#
b00000111 /
11
b00000111 7
b111 ;
#4940000000
0#
01
#4950000000
1#
b00001000 /
11
b00001000 7
b1000 ;
#4960000000
0#
01
#4970000000
1#
b00001001 /
11
b00001001 7
b1001 ;
#4980000000
0#
01
#4990000000
1#
b00001010 /
11
b00001010 7
b1010 ;
#5000000000
0#
01
#5010000000
1#
b00001011 /
11
b00001011 7
b1011 ;
#5020000000
0#
01
#5030000000
1#
b00001100 /
11
b00001100 7
b1100 ;
#5040000000
0#
01
#5050000000
1#
b00001101 /
11
b00001101 7
b1101 ;
#5060000000
0#
01
#5070000000
1#
b00001110 /
11
b00001110 7
b1110 ;
#5080000000
0#
01
#5090000000
1#
b00001111 /
11
b00001111 7
b1111 ;
#5100000000
0#
01
#5110000000
1#
b00010000 /
11
b00010000 7
b10000 ;
#5120000000
0#
01
#5130000000
1#
b00010001 /
11
b00010001 7
b10001 ;
#5140000000
0#
01
#5150000000
1#
b00010010 /
11
b00010010 7
b10010 ;
#5160000000
0#
01
#5170000000
1#
b00010011 /
11
b00010011 7
b10011 ;
#5180000000
0#
01
#5190000000
1#
b00010100 /
11
b00010100 7
b10100 ;
#5200000000
0#
01
#5210000000
1#
b00010101 /
11
b00010101 7
b10101 ;
#5220000000
0#
01
#5230000000
1#
b00010110 /
11
b00010110 7
b10110 ;
#5240000000
0#
01
#5250000000
1#
b00010111 /
11
b00010111 7
b10111 ;
#5260000000
0#
01
#5270000000
1#
b00011000 /
11
b00011000 7
b11000 ;
#5280000000
0#
01
#5290000000
1#
b00011001 /
11
b00011001 7
b11001 ;
#5300000000
0#
01
#5310000000
1#
b00011010 /
11
b00011010 7
b11010 ;
#5320000000
0#
01
#5330000000
1#
b00011011 /
11
b00011011 7
b11011 ;
#5340000000
0#
01
#5350000000
1#
b00011100 /
11
b00011100 7
b11100 ;
#5360000000
0#
01
#5370000000
1#
b00011101 /
11
b00011101 7
b11101 ;
#5380000000
0#
01
#5390000000
1#
b00011110 /
11
b00011110 7
b11110 ;
#5400000000
0#
01
#5410000000
1#
b00011111 /
11
b00011111 7
b11111 ;
#5420000000
0#
01
#5430000000
1#
b00100000 /
11
b00100000 7
b100000 ;
#5440000000
0#
01
#5450000000
1#
b00100001 /
11
b00100001 7
b100001 ;
#5460000000
0#
01
#5470000000
1#
b00100010 /
11
b00100010 7
b100010 ;
#5480000000
0#
01
#5490000000
1#
b00100011 /
11
b00100011 7
b100011 ;
#5500000000
0#
01
#5510000000
1#
b00100100 /
11
b00100100 7
b100100 ;
#5520000000
0#
01
#5530000000
1#
b00100101 /
11
b00100101 7
b100101 ;
#5540000000
0#
01
#5550000000
1#
b00100110 /
11
b00100110 7
b100110 ;
#5560000000
0#
01
#5570000000
1#
b00100111 /
11
b00100111 7
b100111 ;
#5580000000
0#
01
#5590000000
1#
b00101000 /
11
b00101000 7
b101000 ;
#5600000000
0#
01
#5610000000
1#
b00101001 /
11
b00101001 7
b101001 ;
#5620000000
0#
01
#5630000000
1#
b00101010 /
11
b00101010 7
b101010 ;
#5640000000
0#
01
#5650000000
1#
b00101011 /
11
b00101011 7
b101011 ;
#5660000000
0#
01
#5670000000
1#
b00101100 /
11
b00101100 7
b101100 ;
#5680000000
0#
01
#5690000000
1#
b00101101 /
11
b00101101 7
b101101 ;
#5700000000
0#
01
#5710000000
1#
b00101110 /
11
b00101110 7
b101110 ;
#5720000000
0#
01
#5730000000
1#
b00101111 /
11
b00101111 7
b101111 ;
#5740000000
0#
01
#5750000000
1#
b00110000 /
11
b00110000 7
b110000 ;
#5760000000
0#
01
